bk_bscp/__init__.py
bk_bscp/client.py
bk_bscp/constants.py
bk_bscp/exceptions.py
bk_bscp/models.py
bk_bscp/py.typed
bk_bscp/utils.py
bk_bscp/grpc_lib/core/app/app_pb2.py
bk_bscp/grpc_lib/core/app/app_pb2.pyi
bk_bscp/grpc_lib/core/app/app_pb2_grpc.py
bk_bscp/grpc_lib/core/app_template_binding/app_template_binding_pb2.py
bk_bscp/grpc_lib/core/app_template_binding/app_template_binding_pb2.pyi
bk_bscp/grpc_lib/core/app_template_binding/app_template_binding_pb2_grpc.py
bk_bscp/grpc_lib/core/app_template_variable/app_template_variable_pb2.py
bk_bscp/grpc_lib/core/app_template_variable/app_template_variable_pb2.pyi
bk_bscp/grpc_lib/core/app_template_variable/app_template_variable_pb2_grpc.py
bk_bscp/grpc_lib/core/base/base_pb2.py
bk_bscp/grpc_lib/core/base/base_pb2.pyi
bk_bscp/grpc_lib/core/base/base_pb2_grpc.py
bk_bscp/grpc_lib/core/client/client_pb2.py
bk_bscp/grpc_lib/core/client/client_pb2.pyi
bk_bscp/grpc_lib/core/client/client_pb2_grpc.py
bk_bscp/grpc_lib/core/client_event/client_event_pb2.py
bk_bscp/grpc_lib/core/client_event/client_event_pb2.pyi
bk_bscp/grpc_lib/core/client_event/client_event_pb2_grpc.py
bk_bscp/grpc_lib/core/client_query/client_query_pb2.py
bk_bscp/grpc_lib/core/client_query/client_query_pb2.pyi
bk_bscp/grpc_lib/core/client_query/client_query_pb2_grpc.py
bk_bscp/grpc_lib/core/commit/commit_pb2.py
bk_bscp/grpc_lib/core/commit/commit_pb2.pyi
bk_bscp/grpc_lib/core/commit/commit_pb2_grpc.py
bk_bscp/grpc_lib/core/config_item/config_item_pb2.py
bk_bscp/grpc_lib/core/config_item/config_item_pb2.pyi
bk_bscp/grpc_lib/core/config_item/config_item_pb2_grpc.py
bk_bscp/grpc_lib/core/content/content_pb2.py
bk_bscp/grpc_lib/core/content/content_pb2.pyi
bk_bscp/grpc_lib/core/content/content_pb2_grpc.py
bk_bscp/grpc_lib/core/credential/credential_pb2.py
bk_bscp/grpc_lib/core/credential/credential_pb2.pyi
bk_bscp/grpc_lib/core/credential/credential_pb2_grpc.py
bk_bscp/grpc_lib/core/credential_scope/credential_scope_pb2.py
bk_bscp-0.3.0.dist-info/METADATA
bk_bscp-0.3.0.dist-info/WHEEL
bk_bscp-0.3.0.dist-info/licenses/LICENSE.txt
bk_bscp-0.3.0.dist-info/RECORD
