Metadata-Version: 2.3
Name: bk-bscp
Version: 0.3.0
Summary: The Python SDK for blueking bscp project.
Project-URL: Home, https://github.com/TencentBlueKing/bscp-python-sdk
Author-email: blueking <blueking@tencent.com>
License: TencentBlueKing is pleased to support the open source community by making
Classifier: License :: OSI Approved :: MIT License
Classifier: Programming Language :: Python :: 3
Classifier: Programming Language :: Python :: 3 :: Only
Classifier: Programming Language :: Python :: 3.8
Classifier: Programming Language :: Python :: 3.9
Classifier: Programming Language :: Python :: 3.10
Classifier: Programming Language :: Python :: 3.11
Classifier: Programming Language :: Python :: 3.12
Classifier: Programming Language :: Python :: 3.13
Requires-Python: >=3.8
Requires-Dist: grpcio>=1.60.0
Requires-Dist: protobuf>=4.25.2
Requires-Dist: typing-extensions>=4.9.0
